gra/__init__.py
gra/graphs.py
gra/rules.py
gra-0.0.3.dist-info/METADATA
gra-0.0.3.dist-info/WHEEL
gra-0.0.3.dist-info/licenses/LICENSE
gra-0.0.3.dist-info/RECORD
