Metadata-Version: 2.1
Name: gra
Version: 0.0.3
Summary: Package for Graph-Rewriting Automata
Project-URL: Homepage, https://github.com/paulcousin/gra-python
Project-URL: Bug Tracker, https://github.com/paulcousin/gra-python/issues
Author-email: Paul Cousin <cousin.paul@gmail.com>
License-File: LICENSE
Classifier: License :: OSI Approved :: MIT License
Classifier: Operating System :: OS Independent
Classifier: Programming Language :: Python :: 3
Requires-Python: >=3.9
